trepan3k_mathics3/__init__.py
trepan3k_mathics3/mabort.py
trepan3k_mathics3/mathics3.py
trepan3k_mathics3/mbacktrace.py
trepan3k_mathics3/mdown.py
trepan3k_mathics3/mframe.py
trepan3k_mathics3/mprogram.py
trepan3k_mathics3/mup.py
trepan3k_mathics3/printelement.py
trepan3k_mathics3/version.py
trepan3k_mathics3-1.1.0.dist-info/licenses/COPYING
trepan3k_mathics3-1.1.0.dist-info/METADATA
trepan3k_mathics3-1.1.0.dist-info/WHEEL
trepan3k_mathics3-1.1.0.dist-info/top_level.txt
trepan3k_mathics3-1.1.0.dist-info/RECORD
