Metadata-Version: 2.4
Name: trepan3k_mathics3
Version: 1.1.0
Summary: trepan3k plugin to support Mathics3 debugging
Author-email: Rocky Bernstein <rocky@gnu.org>
License-Expression: GPL-3.0-or-later
Project-URL: Homepage, https://github.com/Mathics3/trepan3k-mathics3-plugin
Project-URL: Downloads, https://github.com/Mathics3/trepan3k-mathics3-plugin/releases
Keywords: debugger
Classifier: Development Status :: 3 - Alpha
Classifier: Intended Audience :: Developers
Classifier: Programming Language :: Python
Classifier: Topic :: Software Development :: Libraries :: Python Modules
Classifier: Programming Language :: Python :: 3.10
Classifier: Programming Language :: Python :: 3.11
Classifier: Programming Language :: Python :: 3.12
Classifier: Programming Language :: Python :: 3.13
Classifier: Topic :: Software Development :: Debuggers
License-File: COPYING
Requires-Dist: Mathics3>=9.0.0
Requires-Dist: Mathics3-Module-trepan>=9.0.0
Requires-Dist: trepan3k>=1.4.1
Provides-Extra: dev
Requires-Dist: pre-commit; extra == "dev"
Requires-Dist: pytest; extra == "dev"
Dynamic: license-file
